{"backend":{"koa":[""],"mongodb":[""],"nginx":["","01-install-nginx","02-explain-the-main-configuration-file-of-nginx","03-nginx-basic-operation","04-ubuntu-installs-the-latest-version-of-nginx"]},"frontend":{"css":[""],"javascript":["","array-methods","maybe-optimization-is-needed"],"nodejs":["","01-install-nodejs"],"webpack":["","01-loader"]},"guide":["","about-me"],"more":{"algorithm":[""],"bookmark":[""],"clean":["","docs","javascript","versions"],"hodgepodge":["","restful-api-best-practices"],"interview":["","01-add-large-numbers","02-seo-optimization","03-parse-url-parameter"]},"os":{"centos":["","install-centos-for-the-first-time"],"linux":["","how-to-install-centos-on-virtualbox","how-to-install-manjaro-on-virtualbox","scp","systemd"],"manjaro":["","manjaro-configuration","most-used-softwares","solve-problems-with-manjaro"],"ubuntu":["","add-user","clone-project-to-server","fix-date","generate-ssh-key","login-with-rsa-key"]},"tools":{"git":["","01-git-concept","02-daily-git","gitignore"],"github":["","download-huge-project-from-github","switch-multiple-github-accounts"],"vscode":["","plugins","tricks"]}}